pyked/__init__.py
pyked/_version.py
pyked/chemked.py
pyked/converters.py
pyked/orcid.py
pyked/validation.py
pyked/schemas/chemked_schema.yaml
pyked/schemas/composition_schema.yaml
pyked/schemas/ignition_delay_schema.yaml
pyked/schemas/value_unit_schema.yaml
pyked/tests/__init__.py
pyked/tests/dataframe_st.csv
pyked/tests/rcm_history.csv
pyked/tests/test_chemked.py
pyked/tests/test_converters.py
pyked/tests/test_validation.py
pyked/tests/test_version.py
pyked/tests/testfile_bad.yaml
pyked/tests/testfile_many_species.yaml
pyked/tests/testfile_rcm.xml
pyked/tests/testfile_rcm.yaml
pyked/tests/testfile_rcm2.yaml
pyked/tests/testfile_rcm_old.yaml
pyked/tests/testfile_required.yaml
pyked/tests/testfile_st.xml
pyked/tests/testfile_st.yaml
pyked/tests/testfile_st2.yaml
pyked/tests/testfile_st_p5.yaml
pyked/tests/testfile_st_thermo.yaml
pyked/tests/testfile_uncertainty.yaml
pyked-0.4.1.dist-info/DESCRIPTION.rst
pyked-0.4.1.dist-info/LICENSE.txt
pyked-0.4.1.dist-info/METADATA
pyked-0.4.1.dist-info/RECORD
pyked-0.4.1.dist-info/WHEEL
pyked-0.4.1.dist-info/entry_points.txt
pyked-0.4.1.dist-info/metadata.json
pyked-0.4.1.dist-info/top_level.txt
