Metadata-Version: 2.0
Name: pyked
Version: 0.4.1
Summary: Package for manipulating Chemical Kinetics Experimental Data (ChemKED) files.
Home-page: https://github.com/pr-omethe-us/PyKED
Author: Kyle Niemeyer
Author-email: kyle.niemeyer@gmail.com
License: BSD-3-Clause
Keywords: chemical kinetics
Platform: UNKNOWN
Classifier: Development Status :: 3 - Alpha
Classifier: Intended Audience :: Developers
Classifier: Intended Audience :: Science/Research
Classifier: License :: OSI Approved :: BSD License
Classifier: Natural Language :: English
Classifier: Programming Language :: Python :: 3
Classifier: Programming Language :: Python :: 3.5
Classifier: Programming Language :: Python :: 3.6
Classifier: Topic :: Scientific/Engineering :: Chemistry
Requires-Python: ~=3.5
Requires-Dist: pyyaml (<4.0,>=3.12)
Requires-Dist: cerberus (>=1.0.0)
Requires-Dist: pint (>=0.7.2)
Requires-Dist: numpy (>=1.11.0)
Requires-Dist: habanero (>=0.6.0)
Requires-Dist: uncertainties (>=3.0.1)
Provides-Extra: dataframes
Requires-Dist: pandas; extra == 'dataframes'
